coingecko/__init__.py
coingecko/demo_client.py
coingecko/pro_client.py
coingecko/api/__init__.py
coingecko/api/asset_platform.py
coingecko/api/base.py
coingecko/api/categories.py
coingecko/api/coins.py
coingecko/api/companies.py
coingecko/api/derivatives.py
coingecko/api/error.py
coingecko/api/exchange_rates.py
coingecko/api/exchanges.py
coingecko/api/global_data.py
coingecko/api/nfts.py
coingecko/api/ping.py
coingecko/api/search.py
coingecko/api/simple.py
coingecko/api/utils.py
coingecko/api/pro/__init__.py
coingecko/api/pro/coins.py
coingecko/api/pro/exchanges.py
coingecko/api/pro/global_data.py
coingecko/api/pro/key.py
coingecko/api/pro/nfts.py
coingecko/api/pro/onchain.py
coingecko/api/pro/token_lists.py
coingecko-0.14.dist-info/LICENSE
coingecko-0.14.dist-info/METADATA
coingecko-0.14.dist-info/WHEEL
coingecko-0.14.dist-info/top_level.txt
coingecko-0.14.dist-info/RECORD
