Metadata-Version: 2.1
Name: coingecko
Version: 0.14
Summary: Python wrapper for the CoinGecko API
Home-page: https://github.com/khooihzhz/coingecko-python
Author: khooihzhz
Author-email: khooihongzhe@gmail.com
License: MIT
Classifier: Intended Audience :: Developers
Classifier: License :: OSI Approved :: MIT License
Classifier: Operating System :: OS Independent
Classifier: Programming Language :: Python
Classifier: Programming Language :: Python :: 3
Classifier: Programming Language :: Python :: 3.8
Classifier: Programming Language :: Python :: 3.9
Classifier: Programming Language :: Python :: 3.10
Classifier: Programming Language :: Python :: 3.11
Classifier: Programming Language :: Python :: 3.12
Requires-Python: >=3.0
License-File: LICENSE
Requires-Dist: requests
Provides-Extra: dev
Requires-Dist: pytest-recording ; extra == 'dev'
